[{"metadata":{"name":"default","namespace":"heptio-sonobuoy","selfLink":"/api/v1/namespaces/heptio-sonobuoy/serviceaccounts/default","uid":"1b230ed0-7ddf-11e7-bf00-0ea50f7b4c40","resourceVersion":"1307","creationTimestamp":"2017-08-10T15:18:04Z"},"secrets":[{"name":"default-token-rtb9f"}]},{"metadata":{"name":"sonobuoy-serviceaccount","namespace":"heptio-sonobuoy","selfLink":"/api/v1/namespaces/heptio-sonobuoy/serviceaccounts/sonobuoy-serviceaccount","uid":"1b2ad964-7ddf-11e7-bf00-0ea50f7b4c40","resourceVersion":"1310","creationTimestamp":"2017-08-10T15:18:04Z","labels":{"component":"sonobuoy"},"annotations":{"kubectl.kubernetes.io/last-applied-configuration":"{\"apiVersion\":\"v1\",\"kind\":\"ServiceAccount\",\"metadata\":{\"annotations\":{},\"labels\":{\"component\":\"sonobuoy\"},\"name\":\"sonobuoy-serviceaccount\",\"namespace\":\"heptio-sonobuoy\"}}\n"}},"secrets":[{"name":"sonobuoy-serviceaccount-token-3v3qt"}]}]